Workbook

Sheet Parametri fiscali
A1: Parametri fiscali per accantonamenti futuri
A2: Parametro | B2: Valore | C2: Lettura | D2: Nota
A3: Regime imposta sostitutiva dal 2025 | B3: 0.15 | C3: 15% | D3: Modificabile se cambia regime/aliquota
A4: Coefficiente redditivita professionisti | B4: 0.78 | C4: 78% | D4: Usato nel quadro LM per codice attivita 702209
A5: Aliquota INPS Gestione Separata 2025/2026 | B5: 0.2607 | C5: 26,07% | D5: Da aggiornare quando INPS pubblica nuova aliquota
A6: Accantonamento teorico su incasso | B6: =B4*(B3+B5) -> 0.320346 | C6: 32,0346% | D6: 78% x (15% + 26,07%)
A7: Margine prudenziale extra | B7: 0.01 | C7: 1% | D7: Per arrotondamenti/ritardi/differenze da dichiarazione
A8: Accantonamento prudenziale consigliato | B8: =B6+B7 -> 0.330346 | C8: 33,0346% | D8: Da usare se vuoi stare piu largo
A9: Accantonamento applicato in Fatturazioni | B9: =B8 -> 0.330346 | C9: 32,0346% | D9: Formula applicata nelle prossime righe: prudenziale 78% x (15% + INPS) + 1%

Sheet Riepilogo fiscale
A1: Riepilogo fiscale e riconciliazione documenti
A2: Anno imposta | B2: Ricavi LM | C2: Reddito lordo LM | D2: Contributi dedotti LM | E2: Reddito netto LM | F2: Imposta sostitutiva LM | G2: Acconti imposta versati | H2: Saldo/credito imposta
A3: 2020 | B3: 7380 | C3: 5756 | E3: 5756 | F3: 288 | G3: 0 | H3: 288
A4: 2021 | B4: 37737 | C4: 29435 | D4: 1196 | E4: 28837 | F4: 1442 | G4: 288 | H4: 1154
A5: 2022 | B5: 48264 | C5: 37646 | D5: 0 | E5: 37646 | F5: 1882 | G5: 1442 | H5: 440
A6: 2023 | B6: 41646 | C6: 32484 | D6: 11598 | E6: 20886 | F6: 1044 | G6: 1882 | H6: -838
A7: 2024 | F7: 1191 | G7: 1044 | H7: 147
A9: Anno pagamento | B9: Erario saldo | C9: Erario 1 acconto | D9: Erario 2 acconto | E9: INPS saldo | F9: INPS 1 acconto | G9: INPS 2 acconto | H9: Totale F24 imposte+INPS
A10: 2024 | B10: -838 | C10: 522 | D10: 522 | E10: 621 | F10: 3387.6 | G10: 3387.6 | H10: =SUM(B10:G10) -> 7602.2
A11: 2025 | B11: 147 | C11: 595.5 | D11: 595.5 | E11: 1364 | F11: 3255.6 | G11: 3255.6 | H11: =SUM(B11:G11) -> 9213.2
A13: Controllo | B13: Valore workbook | C13: Valore PDF/F24 | D13: Delta | E13: Esito
A14: Totale pagamenti 2024 | B14: ='Imposte e Tasse'!AG42 -> 9354.2 | C14: =H10 -> 7602.2 | D14: =B14-C14 -> 1752 | E14: =IF(ABS(D14)<0.01,"OK","DA VERIFICARE") -> DA VERIFICARE
A15: Totale pagamenti 2025 | B15: ='Imposte e Tasse'!AN42 -> 7724.2 | C15: =H11 -> 9213.2 | D15: =B15-C15 -> -1489 | E15: =IF(ABS(D15)<0.01,"OK","DA VERIFICARE") -> DA VERIFICARE
A17: Stima annua da incassi Excel | B17: 2025 | C17: 2026
A18: Incassi anno | B18: =SUMIFS(Fatturazioni!$Z$8:$Z$94,Fatturazioni!$A$8:$A$94,">="&DATE(B17,1,1),Fatturazioni!$A$8:$A$94,"<"&DATE(B17+1,1,1)) -> 36666.58 | C18: =SUMIFS(Fatturazioni!$Z$8:$Z$94,Fatturazioni!$A$8:$A$94,">="&DATE(C17,1,1),Fatturazioni!$A$8:$A$94,"<"&DATE(C17+1,1,1)) -> 0
A19: Accantonamento teorico | B19: =B18*'Parametri fiscali'!$B$6 -> 11745.992 | C19: =C18*'Parametri fiscali'!$B$6 -> 0
A20: Accantonamento prudenziale | B20: =B18*'Parametri fiscali'!$B$8 -> 12112.658 | C20: =C18*'Parametri fiscali'!$B$8 -> 0

Sheet Fatturazioni
B1: DIPARTIMENTO PER LO SPORT (STUDIARE SVILUPPO/EUTALIA) | I1: FEI WCH 2022 (FISE/ESE) | N1: MINISTRO SPORT E GIOVANI (SPORT E SALUTE) | S1: MINISTRO SPORT E GIOVANI e DPGSCU (EUTALIA) | Z1: TOTALE INCASSI MENSILI | AA1: ACCANTONAMENTO PER PAGAMENTO TASSE | AG1: NUOVO ACCANTONAMENTO TASSE (parametrico) | AL1: 180 | AM1: 14 | AN1: 300
A3: MESE | B3: GIORNATE FATTURATE | C3: RIMANENZA GIORNATE | D3: IMPORTO FATTURA | E3: IMPORTO RIMANENTE | F3: TOTALE INCASSATO | G3: EMISSIONE FATTURA | H3: SALDO FATTURA | I3: IMPORTO FATTURA | J3: IMPORTO RIMANENTE | K3: TOTALE INCASSATO | L3: EMISSIONE FATTURA | M3: SALDO FATTURA | N3: IMPORTO FATTURA | O3: IMPORTO RIMANENTE | P3: TOTALE INCASSATO | Q3: EMISSIONE FATTURA | R3: SALDO FATTURA | S3: GIORNATE FATTURATE | T3: RIMANENZA GIORNATE | U3: IMPORTO FATTURA | V3: IMPORTO RIMANENTE | W3: TOTALE INCASSATO | X3: EMISSIONE FATTURA | Y3: SALDO FATTURA | AA3: Saldo | AB3: Acconto | AC3: Parziale | AD3: Totale | AE3: Eseguito | AF3: Mancante | AG3: Parziale | AH3: Totale | AI3: Eseguito | AJ3: Mancante
A4: start | B4: =SUM(B8:B17) -> 140 | C4: 140 | E4: =C4*$AL$1 -> 25200 | J4: 25200 | O4: 40000 | S4: =SUM(S73:S79) -> 0 | T4: 97 | V4: 29100
A5: 1° proroga dps | B5: 48 | C5: 48 | E5: =C5*$AL$1 -> 8640
A6: 2° proroga dps | B6: 165 | C6: 165 | E6: =C6*$AL$1 -> 29700
A7: integraz. dps | B7: 3 | C7: 3 | E7: =C7*$AL$1 -> 540
A8: 44075 | B8: 5 | C8: =C4-B8 -> 135 | D8: =B8*$AL$1 -> 900 | E8: =C8*$AL$1 -> 24300 | F8: =D8 -> 900 | G8: 44112 | H8: 44145 | Z8: =D8+I8 -> 900 | AA8: =((Z8*78%)*5%)+((Z8*78%)*25.72%) -> 215.6544 | AB8: =AA8*41.97% -> 90.510152 | AC8: =AA8+AB8 -> 306.16455 | AD8: =AC8 -> 306.16455 | AE8: 0.001 | AF8: =AD8-AE8 -> 306.16355
A9: 44105 | B9: 19 | C9: =C8-B9 -> 116 | D9: =B9*$AL$1 -> 3420 | E9: =C9*$AL$1 -> 20880 | F9: =D9+F8 -> 4320 | G9: 44141 | H9: 44180 | Z9: =D9+I9 -> 3420 | AA9: =((Z9*78%)*5%)+((Z9*78%)*25.72%) -> 819.48672 | AB9: =AA9*41.97% -> 343.93858 | AC9: =AA9+AB9 -> 1163.4253 | AD9: =AD8+AC9 -> 1469.5898 | AE9: 1035.14 | AF9: =AF8+AC9-AE9 -> 434.44885
A10: 44136 | B10: 17 | C10: =C9-B10 -> 99 | D10: =B10*$AL$1 -> 3060 | E10: =C10*$AL$1 -> 17820 | F10: =D10+F9 -> 7380 | G10: 44169 | H10: 44196 | Z10: =D10+I10 -> 3060 | AA10: =((Z10*78%)*5%)+((Z10*78%)*25.72%) -> 733.22496 | AB10: =AA10*41.97% -> 307.73452 | AC10: =AA10+AB10 -> 1040.9595 | AD10: =AD9+AC10 -> 2510.5493 | AE10: 733.23 | AF10: =AF9+AC10-AE10 -> 742.17832
A11: 44166 | B11: 15 | C11: =C10-B11 -> 84 | D11: =B11*$AL$1 -> 2700 | E11: =C11*$AL$1 -> 15120 | F11: =D11+F10 -> 10080 | G11: 44214 | H11: 44229 | Z11: =D11+I11 -> 2700 | AA11: =((Z11*78%)*5%)+((Z11*78%)*25.72%) -> 646.9632 | AB11: =AA11*41.97% -> 271.53046 | AC11: =AA11+AB11 -> 918.49366 | AD11: =AD10+AC11 -> 3429.043 | AE11: 646.96 | AF11: =AF10+AC11-AE11 -> 1013.712
A12: 44197 | B12: 11 | C12: =C11-B12 -> 73 | D12: =B12*$AL$1 -> 1980 | E12: =C12*$AL$1 -> 13140 | F12: =D12+F11 -> 12060 | G12: 44239 | H12: 44249 | Z12: =D12+I12 -> 1980 | AA12: 661 | AB12: =AA12*41.97% -> 277.4217 | AC12: =AA12+AB12 -> 938.4217 | AD12: =AD11+AC12 -> 4367.4647 | AE12: 655.1 | AF12: =AF11+AC12-AE12 -> 1297.0337
A13: 44228 | B13: 19 | C13: =C12-B13 -> 54 | D13: =B13*$AL$1 -> 3420 | E13: =C13*$AL$1 -> 9720 | F13: =D13+F12 -> 15480 | G13: 44260 | H13: 44287 | Z13: =D13+I13 -> 3420 | AA13: 1105 | AB13: =AA13*41.97% -> 463.7685 | AC13: =AA13+AB13 -> 1568.7685 | AD13: =AD12+AC13 -> 5936.2332 | AE13: 1096.13 | AF13: =AF12+AC13-AE13 -> 1769.6722
A14: 44256 | B14: 14 | C14: =C13-B14 -> 40 | D14: =B14*$AL$1 -> 2520 | E14: =C14*$AL$1 -> 7200 | F14: =D14+F13 -> 18000 | G14: 44302 | H14: 44322 | Z14: =D14+I14 -> 2520 | AA14: =((Z14*78%)*5%)+((Z14*78%)*25.98%) -> 608.94288 | AB14: =AA14*41.97% -> 255.57333 | AC14: =AA14+AB14 -> 864.51621 | AD14: =AD13+AC14 -> 6800.7494 | AE14: 603.83 | AF14: =AF13+AC14-AE14 -> 2030.3584
A15: 44287 | B15: 14 | C15: =C14-B15 -> 26 | D15: =B15*$AL$1 -> 2520 | E15: =C15*$AL$1 -> 4680 | F15: =D15+F14 -> 20520 | G15: 44320 | H15: 44354 | Z15: =D15+I15 -> 2520 | AA15: =((Z15*78%)*5%)+((Z15*78%)*25.98%) -> 608.94288 | AB15: =AA15*41.97% -> 255.57333 | AC15: =AA15+AB15 -> 864.51621 | AD15: =AD14+AC15 -> 7665.2656 | AE15: 603.83 | AF15: =AF14+AC15-AE15 -> 2291.0446
A16: 44317 | B16: 15 | C16: =C15-B16 -> 11 | D16: =B16*$AL$1 -> 2700 | E16: =C16*$AL$1 -> 1980 | F16: =D16+F15 -> 23220 | G16: 44351 | H16: 44386 | I16: 1400 | J16: =J4-I16 -> 23800 | K16: =I16 -> 1400 | L16: 44348 | M16: 44369 | Z16: =D16+I16 -> 4100 | AA16: =((Z16*78%)*5%)+((Z16*78%)*25.98%) -> 990.7404 | AB16: =AA16*41.97% -> 415.81375 | AC16: =AA16+AB16 -> 1406.5541 | AD16: =AD15+AC16 -> 9071.8197 | AE16: 335.46 | AF16: =AF15+AC16-AE16 -> 3362.1387
A17: 44348 | B17: 11 | C17: =C16-B17 -> 0 | D17: =B17*$AL$1 -> 1980 | E17: =C17*$AL$1 -> 0 | F17: =D17+F16 -> 25200 | G17: 44378 | H17: 44439 | I17: 1400 | J17: =J16-I17 -> 22400 | K17: =K16+I17 -> 2800 | L17: 44378 | M17: 44384 | Z17: =D17+I17 -> 3380 | AA17: =((Z17*78%)*5%)+((Z17*78%)*25.98%) -> 816.75672 | AB17: =AA17*41.97% -> 342.7928 | AC17: =AA17+AB17 -> 1159.5495 | AD17: =AD16+AC17 -> 10231.369 | AE17: 4521.76 | AF17: =AF16+AC17-AE17 -> -0.071746448
A18: 44378 | B18: 12 | C18: =C5-B18 -> 36 | D18: =B18*$AL$1 -> 2160 | E18: =C18*$AL$1 -> 6480 | F18: =D18+F17 -> 27360 | G18: 44439 | H18: 44468 | I18: 1400 | J18: =J17-I18 -> 21000 | K18: =K17+I18 -> 4200 | L18: 44407 | M18: 44417 | Z18: =D18+I18 -> 3560 | AA18: =((Z18*78%)*5%)+((Z18*78%)*25.98%) -> 860.25264 | AB18: =AA18*41.97% -> 361.04803 | AC18: =AA18+AB18 -> 1221.3007 | AD18: =AD17+AC18 -> 11452.67 | AE18: 1221.3 | AF18: =AF17+AC18-AE18 -> -0.07107344
A19: 44409 | B19: 5 | C19: =C18-B19 -> 31 | D19: =B19*$AL$1 -> 900 | E19: =C19*$AL$1 -> 5580 | F19: =D19+F18 -> 28260 | G19: 44453 | H19: 44509 | I19: 1400 | J19: =J18-I19 -> 19600 | K19: =K18+I19 -> 5600 | L19: 44439 | M19: 44447 | Z19: =D19+I19 -> 2300 | AA19: =((Z19*78%)*5%)+((Z19*78%)*25.98%) -> 555.7812 | AB19: =AA19*41.97% -> 233.26137 | AC19: =AA19+AB19 -> 789.04257 | AD19: =AD18+AC19 -> 12241.712 | AE19: 789 | AF19: =AF18+AC19-AE19 -> -0.0285038
A20: 44440 | B20: 13 | C20: =C19-B20 -> 18 | D20: =B20*$AL$1 -> 2340 | E20: =C20*$AL$1 -> 3240 | F20: =D20+F19 -> 30600 | G20: 44470 | H20: 44532 | I20: 1400 | J20: =J19-I20 -> 18200 | K20: =K19+I20 -> 7000 | L20: 44469 | M20: 44474 | Z20: =D20+I20 -> 3740 | AA20: =((Z20*78%)*5%)+((Z20*78%)*25.98%) -> 903.74856 | AB20: =AA20*41.97% -> 379.30327 | AC20: =AA20+AB20 -> 1283.0518 | AD20: =AD19+AC20 -> 13524.764 | AE20: 0.001 | AF20: =AF19+AC20-AE20 -> 1283.0223
A21: 44470 | B21: 13 | C21: =C20-B21 -> 5 | D21: =B21*$AL$1 -> 2340 | E21: =C21*$AL$1 -> 900 | F21: =D21+F20 -> 32940 | G21: 44508 | H21: 44560 | I21: 1400 | J21: =J20-I21 -> 16800 | K21: =K20+I21 -> 8400 | L21: 44498 | M21: 44511 | Z21: =D21+I21 -> 3740 | AA21: =((Z21*78%)*5%)+((Z21*78%)*25.98%) -> 903.74856 | AB21: =AA21*41.97% -> 379.30327 | AC21: =AA21+AB21 -> 1283.0518 | AD21: =AD20+AC21 -> 14807.816 | AE21: 2566.1511 | AF21: =AF20+AC21-AE21 -> -0.076899908
A22: 44501 | B22: 14 | C22: 156 | D22: =B22*$AL$1 -> 2520 | E22: 28080 | F22: 35460 | G22: 44543 | H22: 44609 | I22: 1400 | J22: =J21-I22 -> 15400 | K22: =K21+I22 -> 9800 | L22: 44530 | M22: 44536 | Z22: =D22+I22 -> 3920 | AA22: =((Z22*78%)*5%)+((Z22*78%)*25.98%) -> 947.24448 | AB22: =AA22*41.97% -> 397.55851 | AC22: =AA22+AB22 -> 1344.803 | AD22: =AD21+AC22 -> 16152.619 | AE22: 0.001 | AF22: =AF21+AC22-AE22 -> 1344.7251
A23: 44531 | B23: 14 | C23: =C22-B23 -> 142 | D23: =B23*$AL$1 -> 2520 | E23: =C23*$AL$1 -> 25560 | F23: =D23+F22 -> 37980 | G23: 44580 | H23: 44621 | I23: 1400 | J23: =J22-I23 -> 14000 | K23: =K22+I23 -> 11200 | L23: 44561 | M23: 44578 | Z23: =D23+I23 -> 3920 | AA23: =((Z23*78%)*5%)+((Z23*78%)*25.98%) -> 947.24448 | AB23: =AA23*41.97% -> 397.55851 | AC23: =AA23+AB23 -> 1344.803 | AD23: =AD22+AC23 -> 17497.422 | AE23: 2690 | AF23: =AF22+AC23-AE23 -> -0.4719234
A24: 44562 | B24: 14 | C24: =C23-B24 -> 128 | D24: =B24*$AL$1 -> 2520 | E24: =C24*$AL$1 -> 23040 | F24: =D24+F23 -> 40500 | G24: 44608 | H24: 44651 | I24: 1800 | J24: =J23-I24+4000 -> 16200 | K24: =K23+I24 -> 13000 | L24: 44592 | M24: 44601 | Z24: =D24+I24 -> 4320 | AA24: =((Z24*78%)*5%)+((Z24*78%)*26.23%) -> 1052.3261 | AB24: =AA24*41.97% -> 441.66126 | AC24: =AA24+AB24 -> 1493.9873 | AD24: =AD23+AC24 -> 18991.409 | AE24: 1494 | AF24: =AF23+AC24-AE24 -> -0.48458762
A25: 44593 | B25: 14 | C25: =C24-B25 -> 114 | D25: =B25*$AL$1 -> 2520 | E25: =C25*$AL$1 -> 20520 | F25: =D25+F24 -> 43020 | G25: 44651 | H25: 44680 | I25: 1800 | J25: =J24-I25 -> 14400 | K25: =K24+I25 -> 14800 | L25: 44620 | M25: 44629 | Z25: =D25+I25 -> 4320 | AA25: =((Z25*78%)*5%)+((Z25*78%)*26.23%) -> 1052.3261 | AB25: =AA25*41.97% -> 441.66126 | AC25: =AA25+AB25 -> 1493.9873 | AD25: =AD24+AC25 -> 20485.397 | AE25: 1494 | AF25: =AF24+AC25-AE25 -> -0.49725184
A26: 44621 | B26: 13 | C26: =C25-B26 -> 101 | D26: =B26*$AL$1 -> 2340 | E26: =C26*$AL$1 -> 18180 | F26: =D26+F25 -> 45360 | G26: 44663 | H26: 44713 | I26: 1800 | J26: =J25-I26 -> 12600 | K26: =K25+I26 -> 16600 | L26: 44651 | M26: 44658 | Z26: =D26+I26 -> 4140 | AA26: =((Z26*78%)*5%)+((Z26*78%)*26.23%) -> 1008.4792 | AB26: =AA26*41.97% -> 423.2587 | AC26: =AA26+AB26 -> 1431.7379 | AD26: =AD25+AC26 -> 21917.135 | AE26: 1431.4 | AF26: =AF25+AC26-AE26 -> -0.15938839
A27: 44652 | B27: 15 | C27: =C26-B27 -> 86 | D27: =B27*$AL$1 -> 2700 | E27: =C27*$AL$1 -> 15480 | F27: =D27+F26 -> 48060 | G27: 44694 | H27: 44750 | I27: 1800 | J27: =J26-I27 -> 10800 | K27: =K26+I27 -> 18400 | L27: 44680 | M27: 44687 | Z27: =D27+I27 -> 4500 | AA27: =((Z27*78%)*5%)+((Z27*78%)*26.23%) -> 1096.173 | AB27: =AA27*41.97% -> 460.06381 | AC27: =AA27+AB27 -> 1556.2368 | AD27: =AD26+AC27 -> 23473.371 | AE27: 1556.4 | AF27: =AF26+AC27-AE27 -> -0.32258029
A28: 44682 | B28: 11 | C28: =C27-B28 -> 75 | D28: =B28*$AL$1 -> 1980 | E28: =C28*$AL$1 -> 13500 | F28: =D28+F27 -> 50040 | G28: 44726 | H28: 44777 | I28: 1800 | J28: =J27-I28 -> 9000 | K28: =K27+I28 -> 20200 | L28: 44712 | M28: 44715 | Z28: =D28+I28 -> 3780 | AA28: =((Z28*78%)*5%)+((Z28*78%)*26.23%) -> 920.78532 | AB28: =AA28*41.97% -> 386.4536 | AC28: =AA28+AB28 -> 1307.2389 | AD28: =AD27+AC28 -> 24780.61 | AE28: 1307 | AF28: =AF27+AC28-AE28 -> -0.083661488
A29: 44713 | B29: 14 | C29: =C28-B29 -> 61 | D29: =B29*$AL$1 -> 2520 | E29: =C29*$AL$1 -> 10980 | F29: =D29+F28 -> 52560 | G29: 44760 | H29: 44805 | I29: 1800 | J29: =J28-I29 -> 7200 | K29: =K28+I29 -> 22000 | L29: 44742 | M29: 44750 | Z29: =D29+I29 -> 4320 | AA29: =((Z29*78%)*5%)+((Z29*78%)*26.23%) -> 1052.3261 | AB29: =AA29*41.97% -> 441.66126 | AC29: =AA29+AB29 -> 1493.9873 | AD29: =AD28+AC29 -> 26274.598 | AE29: 1494 | AF29: =AF28+AC29-AE29 -> -0.096325712
A30: 44743 | B30: 15 | C30: =C29-B30 -> 46 | D30: =B30*$AL$1 -> 2700 | E30: =C30*$AL$1 -> 8280 | F30: =D30+F29 -> 55260 | G30: 44779 | H30: 44833 | I30: 1800 | J30: =J29-I30 -> 5400 | K30: =K29+I30 -> 23800 | L30: 44771 | M30: 44781 | Z30: =D30+I30 -> 4500 | AA30: =((Z30*78%)*5%)+((Z30*78%)*26.23%) -> 1096.173 | AB30: =AA30*41.97% -> 460.06381 | AC30: =AA30+AB30 -> 1556.2368 | AD30: =AD29+AC30 -> 27830.835 | AE30: 1556.4 | AF30: =AF29+AC30-AE30 -> -0.25951761
A31: 44774 | B31: 14 | C31: =C30-B31 -> 32 | D31: =B31*$AL$1 -> 2520 | E31: =C31*$AL$1 -> 5760 | F31: =D31+F30 -> 57780 | G31: 44827 | H31: 44874 | I31: 1800 | J31: =J30-I31 -> 3600 | K31: =K30+I31 -> 25600 | L31: 44802 | M31: 44809 | Z31: =D31+I31 -> 4320 | AA31: =((Z31*78%)*5%)+((Z31*78%)*26.23%) -> 1052.3261 | AB31: =AA31*41.97% -> 441.66126 | AC31: =AA31+AB31 -> 1493.9873 | AD31: =AD30+AC31 -> 29324.822 | AE31: 1494 | AF31: =AF30+AC31-AE31 -> -0.27218184
A32: 44805 | B32: 9 | C32: =C31-B32 -> 23 | D32: =B32*$AL$1 -> 1620 | E32: =C32*$AL$1 -> 4140 | F32: =D32+F31 -> 59400 | G32: 44841 | H32: 44893 | I32: 1800 | J32: =J31-I32 -> 1800 | K32: =K31+I32 -> 27400 | L32: 44832 | M32: 44845 | Z32: =D32+I32 -> 3420 | AA32: =((Z32*78%)*5%)+((Z32*78%)*26.23%) -> 833.09148 | AB32: =AA32*41.97% -> 349.64849 | AC32: =AA32+AB32 -> 1182.74 | AD32: =AD31+AC32 -> 30507.562 | AE32: 1183 | AF32: =AF31+AC32-AE32 -> -0.53220768
A33: 44835 | B33: 17 | C33: =C32-B33 -> 6 | D33: =B33*$AL$1 -> 3060 | E33: =C33*$AL$1 -> 1080 | F33: =D33+F32 -> 62460 | G33: 44876 | H33: 44918 | I33: 1800 | J33: =J32-I33 -> 0 | K33: =K32+I33 -> 29200 | L33: 44860 | M33: 44880 | Z33: =D33+I33 -> 4860 | AA33: =((Z33*78%)*5%)+((Z33*78%)*26.23%) -> 1183.8668 | AB33: =AA33*41.97% -> 496.86891 | AC33: =AA33+AB33 -> 1680.7358 | AD33: =AD32+AC33 -> 32188.298 | AE33: 1680.11 | AF33: =AF32+AC33-AE33 -> 0.093545068
A34: 44866 | B34: 9 | C34: =C33-B34+3 -> 0 | D34: =B34*$AL$1 -> 1620 | E34: =C34*$AL$1 -> 0 | F34: =D34+F33 -> 64080 | G34: 44902 | H34: 44977 | Z34: =D34+I34 -> 1620 | AA34: =((Z34*78%)*5%)+((Z34*78%)*26.23%) -> 394.62228 | AB34: =AA34*41.97% -> 165.62297 | AC34: =AA34+AB34 -> 560.24525 | AD34: =AD33+AC34 -> 32748.543 | AE34: 0.001 | AF34: =AF33+AC34-AE34 -> 560.3378
A35: 44896 | N35: 3333.37 | O35: =$O$4-N35 -> 36666.63 | P35: =N35 -> 3333.37 | Q35: 44915 | R35: 44957 | Z35: =N35 -> 3333.37 | AA35: =((Z35*78%)*5%)+((Z35*78%)*26.23%) -> 811.98893 | AB35: =AA35*41.97% -> 340.79175 | AC35: =AA35+AB35 -> 1152.7807 | AD35: =AD34+AC35 -> 33901.324 | AE35: 1713.1 | AF35: =AF34+AC35-AE35 -> 0.018482432
A36: 44927 | N36: 3333.37 | O36: =O35-N35 -> 33333.26 | P36: =P35+N36 -> 6666.74 | Q36: 44946 | R36: 44978 | Z36: =N36 -> 3333.37 | AA36: =((Z36*78%)*5%)+((Z36*78%)*26.23%) -> 811.98893 | AB36: =AA36*41.97% -> 340.79175 | AC36: =AA36+AB36 -> 1152.7807 | AD36: =AD35+AC36 -> 35054.104 | AE36: 0.001 | AF36: =AF35+AC36-AE36 -> 1152.7982
A37: 44958 | N37: 3333.34 | O37: =O36-N36 -> 29999.89 | P37: =P36+N37 -> 10000.08 | Q37: 44977 | R37: 45015 | Z37: =N37 -> 3333.34 | AA37: =((Z37*78%)*5%)+((Z37*78%)*26.23%) -> 811.98162 | AB37: =AA37*41.97% -> 340.78869 | AC37: =AA37+AB37 -> 1152.7703 | AD37: =AD36+AC37 -> 36206.875 | AE37: 2306 | AF37: =AF36+AC37-AE37 -> -0.43151958
A38: 44986 | N38: 3333.34 | O38: =O37-N37 -> 26666.55 | P38: =P37+N38 -> 13333.42 | Q38: 45005 | R38: 45049 | Z38: =N38 -> 3333.34 | AA38: =((Z38*78%)*5%)+((Z38*78%)*26.23%) -> 811.98162 | AB38: =AA38*41.97% -> 340.78869 | AC38: =AA38+AB38 -> 1152.7703 | AD38: =AD37+AC38 -> 37359.645 | AE38: 0.001 | AF38: =AF37+AC38-AE38 -> 1152.3378
A39: 45017 | N39: 3333.34 | O39: =O38-N38 -> 23333.21 | P39: =P38+N39 -> 16666.76 | Q39: 45036 | R39: 45077 | Z39: =N39 -> 3333.34 | AA39: =((Z39*78%)*5%)+((Z39*78%)*26.23%) -> 811.98162 | AB39: =AA39*41.97% -> 340.78869 | AC39: =AA39+AB39 -> 1152.7703 | AD39: =AD38+AC39 -> 38512.415 | AE39: 0.001 | AF39: =AF38+AC39-AE39 -> 2305.1071
A40: 45047 | N40: 3333.34 | O40: =O39-N39 -> 19999.87 | P40: =P39+N40 -> 20000.1 | Q40: 45066 | R40: 45106 | Z40: =N40 -> 3333.34 | AA40: =((Z40*78%)*5%)+((Z40*78%)*26.23%) -> 811.98162 | AB40: =AA40*41.97% -> 340.78869 | AC40: =AA40+AB40 -> 1152.7703 | AD40: =AD39+AC40 -> 39665.185 | AE40: 3458 | AF40: =AF39+AC40-AE40 -> -0.12258498
A41: 45078 | N41: 3333.34 | O41: =O40-N40 -> 16666.53 | P41: =P40+N41 -> 23333.44 | Q41: 45097 | R41: 45128 | Z41: =N41 -> 3333.34 | AA41: =((Z41*78%)*5%)+((Z41*78%)*26.23%) -> 811.98162 | AB41: =AA41*41.97% -> 340.78869 | AC41: =AA41+AB41 -> 1152.7703 | AD41: =AD40+AC41 -> 40817.956 | AE41: 0.001 | AF41: =AF40+AC41-AE41 -> 1152.6467
A42: 45108 | N42: 3333.34 | O42: =O41-N41 -> 13333.19 | P42: =P41+N42 -> 26666.78 | Q42: 45127 | R42: 45149 | Z42: =N42 -> 3333.34 | AA42: =((Z42*78%)*5%)+((Z42*78%)*26.23%) -> 811.98162 | AB42: =AA42*41.97% -> 340.78869 | AC42: =AA42+AB42 -> 1152.7703 | AD42: =AD41+AC42 -> 41970.726 | AE42: 2305 | AF42: =AF41+AC42-AE42 -> 0.4170381
A43: 45139 | N43: 3333.34 | O43: =O42-N42 -> 9999.85 | P43: =P42+N43 -> 30000.12 | Q43: 45158 | R43: 45197 | Z43: =N43 -> 3333.34 | AA43: =((Z43*78%)*5%)+((Z43*78%)*26.23%) -> 811.98162 | AB43: =AA43*41.97% -> 340.78869 | AC43: =AA43+AB43 -> 1152.7703 | AD43: =AD42+AC43 -> 43123.496 | AE43: 0.001 | AF43: =AF42+AC43-AE43 -> 1153.1863
A44: 45170 | N44: 3333.34 | O44: =O43-N43 -> 6666.51 | P44: =P43+N44 -> 33333.46 | Q44: 45189 | R44: 45226 | Z44: =N44 -> 3333.34 | AA44: =((Z44*78%)*5%)+((Z44*78%)*26.23%) -> 811.98162 | AB44: =AA44*41.97% -> 340.78869 | AC44: =AA44+AB44 -> 1152.7703 | AD44: =AD43+AC44 -> 44276.267 | AE44: 2306 | AF44: =AF43+AC44-AE44 -> -0.043338832
A45: 45200 | N45: 3333.34 | O45: =O44-N44 -> 3333.17 | P45: =P44+N45 -> 36666.8 | Q45: 45219 | R45: 45254 | Z45: =N45 -> 3333.34 | AA45: =((Z45*78%)*5%)+((Z45*78%)*26.23%) -> 811.98162 | AB45: =AA45*41.97% -> 340.78869 | AC45: =AA45+AB45 -> 1152.7703 | AD45: =AD44+AC45 -> 45429.037 | AE45: 0.001 | AF45: =AF44+AC45-AE45 -> 1152.726
A46: 45231 | N46: 3333.2 | O46: 0 | P46: =P45+N46 -> 40000 | Q46: 45250 | R46: 45282 | Z46: =N46 -> 3333.2 | AA46: =((Z46*78%)*5%)+((Z46*78%)*26.23%) -> 811.94752 | AB46: =AA46*41.97% -> 340.77437 | AC46: =AA46+AB46 -> 1152.7219 | AD46: =AD45+AC46 -> 46581.759 | AE46: 2305.4 | AF46: =AF45+AC46-AE46 -> 0.047867984
A47: 45261 | N47: 3333.34 | O47: =$O$4-N47 -> 36666.66 | P47: =N47 -> 3333.34 | Q47: 45280 | R47: 45320 | Z47: =N47 -> 3333.34 | AA47: =((Z47*78%)*5%)+((Z47*78%)*26.23%) -> 811.98162 | AB47: =AA47*41.97% -> 340.78869 | AC47: =AA47+AB47 -> 1152.7703 | AD47: =AD46+AC47 -> 47734.529 | AE47: 0.001 | AF47: =AF46+AC47-AE47 -> 1152.8172
A48: 45292 | N48: 3333.34 | O48: =O47-N48 -> 33333.32 | P48: =P47+N48 -> 6666.68 | Q48: 45313 | R48: 45348 | Z48: =N48 -> 3333.34 | AA48: =((Z48*78%)*5%)+((Z48*78%)*26.23%) -> 811.98162 | AB48: =AA48*41.97% -> 340.78869 | AC48: =AA48+AB48 -> 1152.7703 | AD48: =AD47+AC48 -> 48887.3 | AE48: 2306 | AF48: =AF47+AC48-AE48 -> -0.41250894
A49: 45323 | N49: 3333.34 | O49: =O48-N49 -> 29999.98 | P49: =P48+N49 -> 10000.02 | Q49: 45342 | R49: 45378 | Z49: =N49 -> 3333.34 | AA49: =((Z49*78%)*5%)+((Z49*78%)*26.23%) -> 811.98162 | AB49: =AA49*41.97% -> 340.78869 | AC49: =AA49+AB49 -> 1152.7703 | AD49: =AD48+AC49 -> 50040.07 | AE49: 1152.4 | AF49: =AF48+AC49-AE49 -> -0.042197408
A50: 45352 | N50: 3333.34 | O50: =O49-N50 -> 26666.64 | P50: =P49+N50 -> 13333.36 | Q50: 45371 | R50: 45406 | Z50: =N50 -> 3333.34 | AA50: =((Z50*78%)*5%)+((Z50*78%)*26.23%) -> 811.98162 | AB50: =AA50*41.97% -> 340.78869 | AC50: =AA50+AB50 -> 1152.7703 | AD50: =AD49+AC50 -> 51192.84 | AE50: 0.001 | AF50: =AF49+AC50-AE50 -> 1152.7271
A51: 45383 | N51: 3333.34 | O51: =O50-N51 -> 23333.3 | P51: =P50+N51 -> 16666.7 | Q51: 45404 | R51: 45440 | Z51: =N51 -> 3333.34 | AA51: =((Z51*78%)*5%)+((Z51*78%)*26.23%) -> 811.98162 | AB51: =AA51*41.97% -> 340.78869 | AC51: =AA51+AB51 -> 1152.7703 | AD51: =AD50+AC51 -> 52345.61 | AE51: 2305.4 | AF51: =AF50+AC51-AE51 -> 0.097425664
A52: 45413 | N52: 3333.34 | O52: =O51-N52 -> 19999.96 | P52: =P51+N52 -> 20000.04 | Q52: 45432 | R52: 45469 | Z52: =N52 -> 3333.34 | AA52: =((Z52*78%)*5%)+((Z52*78%)*26.23%) -> 811.98162 | AB52: =AA52*41.97% -> 340.78869 | AC52: =AA52+AB52 -> 1152.7703 | AD52: =AD51+AC52 -> 53498.381 | AE52: 0.001 | AF52: =AF51+AC52-AE52 -> 1152.8667
A53: 45444 | N53: 3333.34 | O53: =O52-N53 -> 16666.62 | P53: =P52+N53 -> 23333.38 | Q53: 45463 | R53: 45499 | Z53: =N53 -> 3333.34 | AA53: =((Z53*78%)*5%)+((Z53*78%)*26.23%) -> 811.98162 | AB53: =AA53*41.97% -> 340.78869 | AC53: =AA53+AB53 -> 1152.7703 | AD53: =AD52+AC53 -> 54651.151 | AE53: 0.001 | AF53: =AF52+AC53-AE53 -> 2305.636
A54: 45474 | N54: 3333.34 | O54: =O53-N54 -> 13333.28 | P54: =P53+N54 -> 26666.72 | Q54: 45493 | R54: 45538 | Z54: =N54 -> 3333.34 | AA54: =((Z54*78%)*5%)+((Z54*78%)*26.23%) -> 811.98162 | AB54: =AA54*41.97% -> 340.78869 | AC54: =AA54+AB54 -> 1152.7703 | AD54: =AD53+AC54 -> 55803.921 | AE54: 3458.4 | AF54: =AF53+AC54-AE54 -> 0.0063602722
A55: 45505 | N55: 3333.34 | O55: =O54-N55 -> 9999.94 | P55: =P54+N55 -> 30000.06 | Q55: 45524 | R55: 45565 | Z55: =N55 -> 3333.34 | AA55: =((Z55*78%)*5%)+((Z55*78%)*26.23%) -> 811.98162 | AB55: =AA55*41.97% -> 340.78869 | AC55: =AA55+AB55 -> 1152.7703 | AD55: =AD54+AC55 -> 56956.692 | AE55: 0.001 | AF55: =AF54+AC55-AE55 -> 1152.7757
A56: 45536 | N56: 3333.34 | O56: =O55-N56 -> 6666.6 | P56: =P55+N56 -> 33333.4 | Q56: 45555 | R56: 45596 | Z56: =N56 -> 3333.34 | AA56: =((Z56*78%)*5%)+((Z56*78%)*26.23%) -> 811.98162 | AB56: =AA56*41.97% -> 340.78869 | AC56: =AA56+AB56 -> 1152.7703 | AD56: =AD55+AC56 -> 58109.462 | AE56: 0.001 | AF56: =AF55+AC56-AE56 -> 2305.545
A57: 45566 | N57: 3333.34 | O57: =O56-N57 -> 3333.26 | P57: =P56+N57 -> 36666.74 | Q57: 45587 | R57: 45623 | Z57: =N57 -> 3333.34 | AA57: =((Z57*78%)*5%)+((Z57*78%)*26.23%) -> 811.98162 | AB57: =AA57*41.97% -> 340.78869 | AC57: =AA57+AB57 -> 1152.7703 | AD57: =AD56+AC57 -> 59262.232 | AE57: 3458 | AF57: =AF56+AC57-AE57 -> 0.31529488
A58: 45597 | N58: 3333.26 | O58: =O57-N58 -> 5.4569682e-12 | P58: =P57+N58 -> 40000 | Q58: 45616 | R58: 45644 | Z58: =N58 -> 3333.26 | AA58: =((Z58*78%)*5%)+((Z58*78%)*26.23%) -> 811.96214 | AB58: =AA58*41.97% -> 340.78051 | AC58: =AA58+AB58 -> 1152.7426 | AD58: =AD57+AC58 -> 60414.975 | AE58: 0.001 | AF58: =AF57+AC58-AE58 -> 1153.0569
A59: 45627 | N59: 3333.42 | O59: =$O$4-N59 -> 36666.58 | P59: =N59 -> 3333.42 | Q59: 45643 | R59: 45649 | Z59: =N59 -> 3333.42 | AA59: =((Z59*78%)*5%)+((Z59*78%)*26.23%) -> 812.00111 | AB59: =AA59*41.97% -> 340.79687 | AC59: =AA59+AB59 -> 1152.798 | AD59: =AD58+AC59 -> 61567.773 | AE59: 2306 | AF59: =AF58+AC59-AE59 -> -0.14508205
A60: 45658 | N60: 3333.34 | O60: =O59-N60 -> 33333.24 | P60: =P59+N60 -> 6666.76 | Q60: 45678 | R60: 45720 | Z60: =N60 -> 3333.34 | AA60: =((Z60*78%)*5%)+((Z60*78%)*26.23%) -> 811.98162 | AB60: =AA60*41.97% -> 340.78869 | AC60: =AA60+AB60 -> 1152.7703 | AD60: =AD59+AC60 -> 62720.543 | AE60: 0.001 | AF60: =AF59+AC60-AE60 -> 1152.6242
A61: 45689 | N61: 3333.34 | O61: =O60-N61 -> 29999.9 | P61: =P60+N61 -> 10000.1 | Q61: 45708 | R61: 45744 | Z61: =N61 -> 3333.34 | AA61: =((Z61*78%)*5%)+((Z61*78%)*26.23%) -> 811.98162 | AB61: =AA61*41.97% -> 340.78869 | AC61: =AA61+AB61 -> 1152.7703 | AD61: =AD60+AC61 -> 63873.314 | AE61: 0.001 | AF61: =AF60+AC61-AE61 -> 2305.3935
A62: 45717 | N62: 3333.34 | O62: =O61-N62 -> 26666.56 | P62: =P61+N62 -> 13333.44 | Q62: 45736 | R62: 45769 | Z62: =N62 -> 3333.34 | AA62: =((Z62*78%)*5%)+((Z62*78%)*26.23%) -> 811.98162 | AB62: =AA62*41.97% -> 340.78869 | AC62: =AA62+AB62 -> 1152.7703 | AD62: =AD61+AC62 -> 65026.084 | AE62: 0.001 | AF62: =AF61+AC62-AE62 -> 3458.1629
A63: 45748 | N63: 3333.34 | O63: =O62-N63 -> 23333.22 | P63: =P62+N63 -> 16666.78 | Q63: 45767 | R63: 45804 | Z63: =N63 -> 3333.34 | AA63: =((Z63*78%)*5%)+((Z63*78%)*26.23%) -> 811.98162 | AB63: =AA63*41.97% -> 340.78869 | AC63: =AA63+AB63 -> 1152.7703 | AD63: =AD62+AC63 -> 66178.854 | AE63: 4611 | AF63: =AF62+AC63-AE63 -> -0.066835904
A64: 45778 | N64: 3333.34 | O64: =O63-N64 -> 19999.88 | P64: =P63+N64 -> 20000.12 | Q64: 45797 | R64: 45839 | Z64: =N64 -> 3333.34 | AA64: =((Z64*78%)*5%)+((Z64*78%)*26.23%) -> 811.98162 | AB64: =AA64*41.97% -> 340.78869 | AC64: =AA64+AB64 -> 1152.7703 | AD64: =AD63+AC64 -> 67331.625 | AE64: 0.0001 | AF64: =AF63+AC64-AE64 -> 1152.7034 | AG64: RIPORTO
A65: 45809 | N65: 3333.34 | O65: =O64-N65 -> 16666.54 | P65: =P64+N65 -> 23333.46 | Q65: 45828 | R65: 45860 | Z65: =N65 -> 3333.34 | AA65: =((Z65*78%)*5%)+((Z65*78%)*26.23%) -> 811.98162 | AB65: =AA65*41.97% -> 340.78869 | AC65: =AA65+AB65 -> 1152.7703 | AD65: =AD64+AC65 -> 68484.395 | AE65: 2305 | AF65: 0.0001 | AG65: 1153 | AH65: 68484 | AI65: 2305 | AJ65: 0
A66: 45839 | N66: 3333.34 | O66: =O65-N66 -> 13333.2 | P66: =P65+N66 -> 26666.8 | Q66: 45858 | R66: 45902 | Z66: =N66 -> 3333.34 | AA66: =((Z66*78%)*5%)+((Z66*78%)*26.23%) -> 811.98162 | AB66: =AA66*41.97% -> 340.78869 | AC66: =AA66+AB66 -> 1152.7703 | AD66: =AD65+AC66 -> 69637.165 | AG66: =IF(Z66=0,"",ROUND(Z66*'Parametri fiscali'!$B$9,2)) -> 1101.16 | AH66: =IF(AG66="","",AH65+AG66) -> 69585.16 | AJ66: =IF(AG66="","",AJ65+AG66-AI66) -> 1101.16
A67: 45870 | N67: 3333.34 | O67: =O66-N67 -> 9999.86 | P67: =P66+N67 -> 30000.14 | Q67: 45889 | R67: 45926 | Z67: =N67 -> 3333.34 | AA67: =((Z67*78%)*5%)+((Z67*78%)*26.23%) -> 811.98162 | AB67: =AA67*41.97% -> 340.78869 | AC67: =AA67+AB67 -> 1152.7703 | AD67: =AD66+AC67 -> 70789.935 | AG67: =IF(Z67=0,"",ROUND(Z67*'Parametri fiscali'!$B$9,2)) -> 1101.16 | AH67: =IF(AG67="","",AH66+AG67) -> 70686.32 | AJ67: =IF(AG67="","",AJ66+AG67-AI67) -> 2202.32
A68: 45901 | N68: 3333.34 | O68: =O67-N68 -> 6666.52 | P68: =P67+N68 -> 33333.48 | Q68: 45920 | R68: 45954 | Z68: =N68 -> 3333.34 | AA68: =((Z68*78%)*5%)+((Z68*78%)*26.23%) -> 811.98162 | AB68: =AA68*41.97% -> 340.78869 | AC68: =AA68+AB68 -> 1152.7703 | AD68: =AD67+AC68 -> 71942.706 | AG68: =IF(Z68=0,"",ROUND(Z68*'Parametri fiscali'!$B$9,2)) -> 1101.16 | AH68: =IF(AG68="","",AH67+AG68) -> 71787.48 | AJ68: =IF(AG68="","",AJ67+AG68-AI68) -> 3303.48
A69: 45931 | N69: 3333.34 | O69: =O68-N69 -> 3333.18 | P69: =P68+N69 -> 36666.82 | Q69: 45950 | R69: 45989 | Z69: =N69 -> 3333.34 | AA69: =((Z69*78%)*5%)+((Z69*78%)*26.23%) -> 811.98162 | AB69: =AA69*41.97% -> 340.78869 | AC69: =AA69+AB69 -> 1152.7703 | AD69: =AD68+AC69 -> 73095.476 | AG69: =IF(Z69=0,"",ROUND(Z69*'Parametri fiscali'!$B$9,2)) -> 1101.16 | AH69: =IF(AG69="","",AH68+AG69) -> 72888.64 | AJ69: =IF(AG69="","",AJ68+AG69-AI69) -> 4404.64 | AK69: Saldo CC | AL69: 7534.41
A70: 45962 | N70: 3333.18 | O70: =O69-N70 -> 4.0927262e-12 | P70: =P69+N70 -> 40000 | Q70: 45980 | R70: 46013 | Z70: =N70 -> 3333.18 | AA70: =((Z70*78%)*5%)+((Z70*78%)*26.23%) -> 811.94265 | AB70: =AA70*41.97% -> 340.77233 | AC70: =AA70+AB70 -> 1152.715 | AD70: =AD69+AC70 -> 74248.191 | AG70: =IF(Z70=0,"",ROUND(Z70*'Parametri fiscali'!$B$9,2)) -> 1101.1 | AH70: =IF(AG70="","",AH69+AG70) -> 73989.74 | AJ70: =IF(AG70="","",AJ69+AG70-AI70) -> 5505.74 | AK70: <----- | AL70: Vers. To-do
A71: 45992 | Z71: =U71 -> 0 | AG71: =IF(Z71=0,"",ROUND(Z71*'Parametri fiscali'!$B$9,2)) | AH71: =IF(AG71="","",AH70+AG71) | AJ71: =IF(AG71="","",AJ70+AG71-AI71)
A72: 46023 | Z72: =U72 -> 0 | AG72: =IF(Z72=0,"",ROUND(Z72*'Parametri fiscali'!$B$9,2)) | AH72: =IF(AG72="","",AH71+AG72) | AJ72: =IF(AG72="","",AJ71+AG72-AI72) | AK72: Dal rigo 66: AG usa Parametri fiscali!B9
A73: 46054 | T73: =T4-$S$73 -> 97 | U73: =S73*$AN$1 -> 0 | V73: =T73*$AN$1 -> 29100 | W73: =W72+U73 -> 0 | Z73: =U73 -> 0 | AG73: =IF(Z73=0,"",ROUND(Z73*'Parametri fiscali'!$B$9,2)) | AH73: =IF(AG73="","",AH72+AG73) | AJ73: =IF(AG73="","",AJ72+AG73-AI73) | AK73: Ora B9 punta al valore prudenziale: 33,0346%
A74: 46082 | T74: =T73-S74 -> 97 | U74: =S74*$AN$1 -> 0 | V74: =T74*$AN$1 -> 29100 | W74: =W73+U74 -> 0 | Z74: =U74 -> 0 | AG74: =IF(Z74=0,"",ROUND(Z74*'Parametri fiscali'!$B$9,2)) | AH74: =IF(AG74="","",AH73+AG74) | AJ74: =IF(AG74="","",AJ73+AG74-AI74)
A75: 46113 | T75: =T74-S75 -> 97 | U75: =S75*$AN$1 -> 0 | V75: =T75*$AN$1 -> 29100 | W75: =W74+U75 -> 0 | Z75: =U75 -> 0 | AG75: =IF(Z75=0,"",ROUND(Z75*'Parametri fiscali'!$B$9,2)) | AH75: =IF(AG75="","",AH74+AG75) | AJ75: =IF(AG75="","",AJ74+AG75-AI75)
A76: 46143 | T76: =T75-S76 -> 97 | U76: =S76*$AN$1 -> 0 | V76: =T76*$AN$1 -> 29100 | W76: =W75+U76 -> 0 | Z76: =U76 -> 0 | AG76: =IF(Z76=0,"",ROUND(Z76*'Parametri fiscali'!$B$9,2)) | AH76: =IF(AG76="","",AH75+AG76) | AJ76: =IF(AG76="","",AJ75+AG76-AI76)
A77: 46174 | T77: =T76-S77 -> 97 | U77: =S77*$AN$1 -> 0 | V77: =T77*$AN$1 -> 29100 | W77: =W76+U77 -> 0 | Z77: =U77 -> 0 | AG77: =IF(Z77=0,"",ROUND(Z77*'Parametri fiscali'!$B$9,2)) | AH77: =IF(AG77="","",AH76+AG77) | AJ77: =IF(AG77="","",AJ76+AG77-AI77)
A78: 46204 | T78: =T77-S78 -> 97 | U78: =S78*$AN$1 -> 0 | V78: =T78*$AN$1 -> 29100 | W78: =W77+U78 -> 0 | Z78: =U78 -> 0 | AG78: =IF(Z78=0,"",ROUND(Z78*'Parametri fiscali'!$B$9,2)) | AH78: =IF(AG78="","",AH77+AG78) | AJ78: =IF(AG78="","",AJ77+AG78-AI78)
A79: 46235 | T79: =T78-S79 -> 97 | U79: =S79*$AN$1 -> 0 | V79: =T79*$AN$1 -> 29100 | W79: =W78+U79 -> 0 | Z79: =U79 -> 0 | AG79: =IF(Z79=0,"",ROUND(Z79*'Parametri fiscali'!$B$9,2)) | AH79: =IF(AG79="","",AH78+AG79) | AJ79: =IF(AG79="","",AJ78+AG79-AI79)
A80: 46266 | Z80: =U80 -> 0 | AG80: =IF(Z80=0,"",ROUND(Z80*'Parametri fiscali'!$B$9,2)) | AH80: =IF(AG80="","",AH79+AG80) | AJ80: =IF(AG80="","",AJ79+AG80-AI80)
A81: 46296 | Z81: =U81 -> 0 | AG81: =IF(Z81=0,"",ROUND(Z81*'Parametri fiscali'!$B$9,2)) | AH81: =IF(AG81="","",AH80+AG81) | AJ81: =IF(AG81="","",AJ80+AG81-AI81)
A82: 46327 | Z82: =U82 -> 0 | AG82: =IF(Z82=0,"",ROUND(Z82*'Parametri fiscali'!$B$9,2)) | AH82: =IF(AG82="","",AH81+AG82) | AJ82: =IF(AG82="","",AJ81+AG82-AI82)
A83: 46357 | Z83: =U83 -> 0 | AG83: =IF(Z83=0,"",ROUND(Z83*'Parametri fiscali'!$B$9,2)) | AH83: =IF(AG83="","",AH82+AG83) | AJ83: =IF(AG83="","",AJ82+AG83-AI83)
A84: 46388 | Z84: =U84 -> 0 | AG84: =IF(Z84=0,"",ROUND(Z84*'Parametri fiscali'!$B$9,2)) | AH84: =IF(AG84="","",AH83+AG84) | AJ84: =IF(AG84="","",AJ83+AG84-AI84)
A85: 46419 | Z85: =U85 -> 0 | AG85: =IF(Z85=0,"",ROUND(Z85*'Parametri fiscali'!$B$9,2)) | AH85: =IF(AG85="","",AH84+AG85) | AJ85: =IF(AG85="","",AJ84+AG85-AI85)
A86: 46447 | Z86: =U86 -> 0 | AG86: =IF(Z86=0,"",ROUND(Z86*'Parametri fiscali'!$B$9,2)) | AH86: =IF(AG86="","",AH85+AG86) | AJ86: =IF(AG86="","",AJ85+AG86-AI86)
A87: 46478 | Z87: =U87 -> 0 | AG87: =IF(Z87=0,"",ROUND(Z87*'Parametri fiscali'!$B$9,2)) | AH87: =IF(AG87="","",AH86+AG87) | AJ87: =IF(AG87="","",AJ86+AG87-AI87)
A88: 46508 | Z88: =U88 -> 0 | AG88: =IF(Z88=0,"",ROUND(Z88*'Parametri fiscali'!$B$9,2)) | AH88: =IF(AG88="","",AH87+AG88) | AJ88: =IF(AG88="","",AJ87+AG88-AI88)
A89: 46539 | Z89: =U89 -> 0 | AG89: =IF(Z89=0,"",ROUND(Z89*'Parametri fiscali'!$B$9,2)) | AH89: =IF(AG89="","",AH88+AG89) | AJ89: =IF(AG89="","",AJ88+AG89-AI89)
A90: 46569 | Z90: =U90 -> 0 | AG90: =IF(Z90=0,"",ROUND(Z90*'Parametri fiscali'!$B$9,2)) | AH90: =IF(AG90="","",AH89+AG90) | AJ90: =IF(AG90="","",AJ89+AG90-AI90)
A91: 46600 | Z91: =U91 -> 0 | AG91: =IF(Z91=0,"",ROUND(Z91*'Parametri fiscali'!$B$9,2)) | AH91: =IF(AG91="","",AH90+AG91) | AJ91: =IF(AG91="","",AJ90+AG91-AI91)
... A94: 46692 | Z94: =U94 -> 0 | AG94: =IF(Z94=0,"",ROUND(Z94*'Parametri fiscali'!$B$9,2)) | AH94: =IF(AG94="","",AH93+AG94) | AJ94: =IF(AG94="","",AJ93+AG94-AI94)
A95: 46722

Sheet Missioni e Rimborsi
A1: MISSIONE | B1: PERIODO | C1: IMP. FATT. | D1: NOTA SPESE | E1: FATTURA | F1: SALDATO | G1: IMPORTO | H1: Parziale | I1: Totale | J1: Eseguito | K1: Mancante
A2: Sopralluogo Campionati Mondiali Sci Alpino | B2: 28-30/01/21 | C2: =G2+(G2*4%) -> 784.1184 | D2: ok | E2: 44239 | F2: 44249 | G2: 753.96 | H2: =((G2*78%)*5%)+((G2*78%)*25.98%) -> 182.18991 | I2: =H2 -> 182.18991 | J2: 182.19 | K2: =I2-J2 -> -8.976e-05
A3: Campionati Mondiali di Sci Alpino | B3: 3-21/02/21 | C3: =G3+(G3*4%) -> 1200.7112 | D3: ok | E3: 44260 | F3: 44287 | G3: 1154.53 | H3: =((G3*78%)*5%)+((G3*78%)*25.98%) -> 278.98525 | I3: =H3+I2 -> 461.17516 | J3: 278.99 | K3: =K2+H3-J3 -> -0.00484244
A4: CCI 1*-2*-3*-4* @ Pratoni del Vivaro | B4: 4-7/11/21 | C4: 152.92 | D4: ok | E4: 44510 | F4: 44629 | G4: 152.92 | H4: =((G4*78%)*5%)+((G4*78%)*25.98%) -> 36.9522 | I4: =H4+I3 -> 498.12736 | J4: 36.95 | K4: =K3+H4-J4 -> -0.00264196
A5: Libyan Final Six Milano 2025 | B5: 28/7-7/8/25 | C5: 0 | D5: ok | E5: no fattura | F5: 45958 | G5: 1327.9 | H5: 0 | I5: 0 | J5: 0 | K5: 0 | L5: no fattura | M5: 1391.67

Sheet Contratti
B1: Data Firma | C1: Dati Contratto | D1: Ente | E1: Lavoro | F1: Tipologia | G1: Inizio | H1: Fine | I1: Importo | J1: Giornate | K1: €/giornata | L1: Stato | N1: Conteggi annuali
B3: 44076 | C3: Prot. 034012/StSv | D3: STUDIARE SVILUPPO | E3: DIPARTIMENTO PER LO SPORT | F3: Incarico | G3: 44075 | H3: 44377 | I3: 25200 | J3: 140gg | K3: 180 | L3: terminato | O3: DPS | P3: FISE | Q3: SES | R3: DPGSCU | S3: TOT. | T3: G.T.
N4: Incassi 2020 | O4: 10080 | P4: 0 | Q4: 0 | R4: 0 | S4: =O4+P4+Q4+R4 -> 10080 | T4: =SUM(S4:S10) -> 242380
B5: 44315 | C5: - | D5: FISE-ESE | E5: FEI WCH 2022 | F5: Incarico | G5: 44317 | H5: 44863 | I5: 25200 | J5: - | K5: - | L5: terminato | N5: Incassi 2021 | O5: 27900 | P5: 11200 | Q5: 0 | R5: 0 | S5: =O5+P5+Q5+R5 -> 39100
N6: Incassi 2022 | O6: 26100 | P6: 18000 | R6: 0 | S6: =O6+P6+Q6+R6 -> 44100
B7: 44377 | C7: Prot. 41528/StSv | D7: STUDIARE SVILUPPO | E7: DIPARTIMENTO PER LO SPORT | F7: Proroga | G7: 44378 | H7: 44515 | I7: 8640 | J7: 48gg | K7: 180 | L7: terminato | N7: Incassi 2023 | O7: 0 | P7: 0 | Q7: 40000 | R7: 0 | S7: =O7+P7+Q7+R7 -> 40000
N8: Incassi 2024 | O8: 0 | P8: 0 | Q8: 40000 | R8: 0 | S8: =O8+P8+Q8+R8 -> 40000
B9: 44589 | C9: - | D9: FISE-ESE | E9: FEI WCH 2022 | F9: Integrazione | G9: 44197 | H9: 44863 | I9: 4000 | J9: - | K9: - | L9: terminato | N9: Incassi 2025 | O9: 0 | P9: 0 | Q9: 40000 | R9: 0 | S9: =O9+P9+Q9+R9 -> 40000
N10: Incassi 2026 | O10: 0 | P10: 0 | Q10: 0 | R10: 29100 | S10: =O10+P10+Q10+R10 -> 29100
B11: 44515 | C11: Prot. 45069/StSv | D11: STUDIARE SVILUPPO | E11: DIPARTIMENTO PER LO SPORT | F11: Proroga | G11: 44516 | H11: 44880 | I11: 29700 | J11: 165gg | K11: 180 | L11: terminato
N12: Totali ente | O12: =SUM(O4:O10) -> 64080 | P12: =SUM(P4:P10) -> 29200 | Q12: =SUM(Q4:Q10) -> 120000 | R12: =SUM(R4:R10) -> 29100 | S12: =SUM(S4:S10) -> 242380
B13: 44872 | C13: Prot. 55993/EUT | D13: STUDIARE SVILUPPO | E13: DIPARTIMENTO PER LO SPORT | F13: Integrazione | G13: 44880 | H13: 44880 | I13: 540 | J13: 3gg | K13: 180 | L13: terminato
N14: Conteggi annuali effettivi da fatture
B15: 44907 | C15: Cnt. 2066854 | D15: SPORT E SALUTE | E15: DPGSCU - MIN. SPORT E GIOVANI | F15: Incarico | G15: 44897 | H15: 45261 | I15: 40000 | J15: - | K15: - | L15: terminato
O16: DPS | P16: FISE | Q16: SES | R16: DPGSCU | S16: TOT. | T16: G.T.
B17: 45260 | C17: Cnt. 2071022 | D17: SPORT E SALUTE | E17: MINISTRO SPORT E GIOVANI | F17: Incarico | G17: 45262 | H17: 45627 | I17: 40000 | J17: - | K17: - | L17: terminato | N17: Incassi 2020 | O17: =SUM(Fatturazioni!D8:D11) -> 10080 | P17: =SUM(Fatturazioni!I8:I11) -> 0 | Q17: =SUM(Fatturazioni!N8:N11) -> 0 | R17: 0 | S17: =O17+P17+Q17+R17 -> 10080 | T17: =SUM(S17:S23) -> 213280
N18: Incassi 2021 | O18: =SUM(Fatturazioni!D12:D23) -> 27900 | P18: =SUM(Fatturazioni!I12:I23) -> 11200 | Q18: =SUM(Fatturazioni!N12:N23) -> 0 | R18: 0 | S18: =O18+P18+Q18+R18 -> 39100
B19: 45629 | C19: Cnt. 2075155 | D19: SPORT E SALUTE | E19: MINISTRO SPORT E GIOVANI | F19: Incarico | G19: 45628 | H19: 45992 | I19: 40000 | J19: - | K19: - | L19: terminato | N19: Incassi 2022 | O19: =SUM(Fatturazioni!D24:D35) -> 26100 | P19: =SUM(Fatturazioni!I24:I35) -> 18000 | Q19: =SUM(Fatturazioni!N24:N35) -> 3333.37 | R19: 0 | S19: =O19+P19+Q19+R19 -> 47433.37
N20: Incassi 2023 | O20: =SUM(Fatturazioni!D36:D46) -> 0 | P20: =SUM(Fatturazioni!I36:I47) -> 0 | Q20: =SUM(Fatturazioni!N36:N47) -> 39999.97 | R20: 0 | S20: =O20+P20+Q20+R20 -> 39999.97
B21: 45629 | C21: Prot. 81220/EUT | D21: EUTALIA | E21: DPGSCU - MIN. SPORT E GIOVANI | F21: Incarico | G21: 46062 | H21: 46265 | I21: 29100 | J21: 97gg | K21: 300 | L21: in corso | N21: Incassi 2024 | O21: 0 | P21: 0 | Q21: =SUM(Fatturazioni!N48:N59) -> 40000.08 | R21: 0 | S21: =O21+P21+Q21+R21 -> 40000.08
N22: Incassi 2025 | O22: 0 | P22: 0 | Q22: =SUM(Fatturazioni!N60:N71) -> 36666.58 | R22: 0 | S22: =O22+P22+Q22+R22 -> 36666.58
N23: Incassi 2026 | O23: 0 | P23: 0 | Q23: 0 | R23: =SUM(Fatturazioni!U73:U79) -> 0 | S23: =O23+P23+Q23+R23 -> 0
N25: Totali ente | O25: =SUM(O17:O23) -> 64080 | P25: =SUM(P17:P23) -> 29200 | Q25: =SUM(Q17:Q23) -> 120000 | R25: =SUM(R17:R23) -> 0 | S25: Mancanti | T25: =T17-T4 -> -29100

Sheet Imposte e Tasse
C3: DICHIARAZIONE REDDITI 2021 - PERIODO D'IMPOSTA 2020 | J3: DICHIARAZIONE REDDITI 2022 - PERIODO D'IMPOSTA 2021 | Q3: DICHIARAZIONE REDDITI 2023 - PERIODO D'IMPOSTA 2022 | X3: DICHIARAZIONE REDDITI 2024 - PERIODO D'IMPOSTA 2023 | AE3: DICHIARAZIONE REDDITI 2025 - PERIODO D'IMPOSTA 2024 | AL3: DICHIARAZIONE REDDITI 2026 - PERIODO D'IMPOSTA 2025
C5: ERARIO 2020 | D5: Importo | E5: Data Vers. | F5: Interessi | J5: ERARIO 2021 | K5: Importo | L5: Data Vers. | M5: Interessi | Q5: ERARIO 2022 | R5: Importo | S5: Data Vers. | T5: Interessi | X5: ERARIO 2023 | Y5: Importo | Z5: Data Vers. | AA5: Interessi | AE5: ERARIO 2024 | AF5: Importo | AG5: Data Vers. | AH5: Interessi | AL5: ERARIO 2025 | AM5: Importo | AN5: Data Vers. | AO5: Interessi
C7: SALDO 2020 | D7: 288 | E7: 44398 | F7: 0 | J7: SALDO 2021 | K7: 1158.62 | L7: 44794 | M7: 0 | Q7: SALDO 2022 | R7: 441.76 | S7: 45131 | T7: 0 | X7: SALDO 2023 | Y7: -838 | Z7: 45492 | AA7: 0 | AE7: SALDO 2024 | AF7: 147 | AG7: 45845 | AH7: 0 | AL7: SALDO 2025
C8: 1° ACCONTO 2021 | D8: 144 | E8: 44398 | F8: 0 | J8: 1° ACCONTO 2022 | K8: 723.88 | L8: 44794 | M8: 0 | Q8: 1° ACCONTO 2023 | R8: 944.76 | S8: 45131 | T8: 0 | X8: 1° ACCONTO 2024 | Y8: 522 | Z8: 45492 | AA8: 0 | AE8: 1° ACCONTO 2025 | AF8: 595.5 | AG8: 45845 | AH8: 0 | AL8: 1° ACCONTO 2026
C9: 2° ACCONTO 2021 | D9: 144 | E9: 44530 | F9: 0 | J9: 2° ACCONTO 2022 | K9: 721 | L9: 44890 | M9: 0 | Q9: 2° ACCONTO 2023 | R9: 941 | S9: 45257 | T9: 0 | X9: 2° ACCONTO 2024 | Y9: 522 | Z9: 45629 | AA9: 0 | AE9: 2° ACCONTO 2025 | AF9: 595.5 | AG9: 45988 | AH9: 0 | AL9: 2° ACCONTO 2026
C11: INPS 2020 | D11: Importo | E11: Data Vers. | F11: Interessi | J11: INPS 2021 | K11: Importo | L11: Data Vers. | M11: Interessi | Q11: INPS 2022 | R11: Importo | S11: Data Vers. | T11: Interessi | X11: INPS 2023 | Y11: Importo | Z11: Data Vers. | AA11: Interessi | AE11: INPS 2024 | AF11: Importo | AG11: Data Vers. | AH11: Interessi | AL11: INPS 2025 | AM11: Importo | AN11: Data Vers. | AO11: Interessi
C13: SALDO 2020 | D13: 1480 | E13: 44398 | F13: 0 | J13: SALDO 2021 | K13: 6451 | L13: 44794 | M13: 25.8 | Q13: SALDO 2022 | R13: 3698 | S13: 45131 | T13: 14.79 | X13: SALDO 2023 | Y13: 621 | Z13: 45492 | AA13: 0 | AE13: SALDO 2024 | AF13: 1364 | AG13: 45845 | AH13: 0 | AL13: SALDO 2025
C14: 1° ACCONTO 2021 | D14: 598 | E14: 44398 | F14: 0 | J14: 1° ACCONTO 2022 | K14: 3088.4 | L14: 44794 | M14: 12.35 | Q14: 1° ACCONTO 2023 | R14: 3950 | S14: 45131 | T14: 15.8 | X14: 1° ACCONTO 2024 | Y14: 3387.6 | Z14: 45492 | AA14: 0 | AE14: 1° ACCONTO 2025 | AF14: 3255.6 | AG14: 45845 | AH14: 0 | AL14: 1° ACCONTO 2026
C15: 2° ACCONTO 2021 | D15: 598 | E15: 44530 | F15: 0 | J15: 2° ACCONTO 2022 | K15: 3088.4 | L15: 44890 | M15: 0 | Q15: 2° ACCONTO 2023 | R15: 3950 | S15: 45257 | T15: 0 | X15: 2° ACCONTO 2024 | Y15: 3387.6 | Z15: 45629 | AA15: 0 | AE15: 2° ACCONTO 2025 | AF15: 3255.6 | AG15: 45988 | AH15: 0 | AL15: 2° ACCONTO 2026
C17: BOLLI FATT. 2021 | D17: Importo | E17: Data Vers. | F17: Interessi | J17: BOLLI FATT. 2022 | K17: Importo | L17: Data Vers. | M17: Interessi | Q17: BOLLI FATT. 2023 | R17: Importo | S17: Data Vers. | T17: Interessi | X17: BOLLI FATT. 2024 | Y17: Importo | Z17: Data Vers. | AA17: Interessi | AE17: BOLLI FATT. 2024 | AF17: Importo | AG17: Data Vers. | AH17: Interessi | AL17: BOLLI FATT. 2025 | AM17: Importo | AN17: Data Vers. | AO17: Interessi
C19: 1° TRIMESTRE '21 | D19: 6 | E19: 44530 | F19: 0 | J19: 1° TRIMESTRE '22 | K19: 8 | L19: 44894 | M19: 0 | Q19: 1° TRIMESTRE '23 | R19: 6 | S19: 45257 | T19: 0 | X19: 1° TRIMESTRE '24 | Y19: 6 | Z19: 45622 | AA19: 0 | AE19: 1° TRIMESTRE '25 | AF19: 6 | AG19: 45988 | AH19: 0 | AL19: 1° TRIMESTRE '26
C20: 2° TRIMESTRE '21 | D20: 8 | E20: 44530 | F20: 0 | J20: 2° TRIMESTRE '22 | K20: 16 | L20: 44894 | M20: 0 | Q20: 2° TRIMESTRE '23 | R20: 6 | S20: 45257 | T20: 0 | X20: 2° TRIMESTRE '24 | Y20: 6 | Z20: 45622 | AA20: 0 | AE20: 2° TRIMESTRE '25 | AF20: 6 | AG20: 45988 | AH20: 0 | AL20: 2° TRIMESTRE '26
C21: 3° TRIMESTRE '21 | D21: 14 | E21: 44530 | F21: 0 | J21: 3° TRIMESTRE '22 | K21: 12 | L21: 44894 | M21: 0 | Q21: 3° TRIMESTRE '23 | R21: 6 | S21: 45257 | T21: 0 | X21: 3° TRIMESTRE '24 | Y21: 6 | Z21: 45622 | AA21: 0 | AE21: 3° TRIMESTRE '25 | AF21: 6 | AG21: 45988 | AH21: 0 | AL21: 3° TRIMESTRE '26
C22: 4° TRIMESTRE '21 | D22: 14 | E22: 44620 | J22: 4° TRIMESTRE '22 | K22: 10 | L22: 44984 | M22: 0 | Q22: 4° TRIMESTRE '23 | R22: 6 | S22: 45351 | T22: 0 | X22: 4° TRIMESTRE '24 | Y22: 6 | Z22: 45714 | AA22: 0 | AE22: 4° TRIMESTRE '25 | AF22: 4 | AG22: 46083 | AH22: 0 | AL22: 4° TRIMESTRE '26
C25: CALCOLO TOTALE VERSAMENTI | J25: CALCOLO TOTALE VERSAMENTI | Q25: CALCOLO TOTALE VERSAMENTI | X25: CALCOLO TOTALE VERSAMENTI | AE25: CALCOLO TOTALE VERSAMENTI | AL25: CALCOLO TOTALE VERSAMENTI
C27: SALDO ERARIO 2020 | E27: =D7 -> 288 | J27: SALDO ERARIO 2021 | L27: =K7 -> 1158.62 | Q27: SALDO ERARIO 2022 | S27: =R7 -> 441.76 | X27: SALDO ERARIO 2023 | Z27: =Y7 -> -838 | AE27: SALDO ERARIO 2024 | AG27: =AF7 -> 147 | AL27: SALDO ERARIO 2025 | AN27: =AM7 -> 0
C28: ACCONTO ERARIO 2021 | E28: =D8+D9 -> 288 | J28: ACCONTO ERARIO 2022 | L28: =K8+K9 -> 1444.88 | Q28: ACCONTO ERARIO 2023 | S28: =R8+R9 -> 1885.76 | X28: ACCONTO ERARIO 2024 | Z28: =Y8+Y9 -> 1044 | AE28: ACCONTO ERARIO 2025 | AG28: =AF8+AF9 -> 1191 | AL28: ACCONTO ERARIO 2026 | AN28: =AM8+AM9 -> 0
C30: SALDO INPS 2020 | E30: =D13 -> 1480 | J30: SALDO INPS 2021 | L30: =K13 -> 6451 | Q30: SALDO INPS 2022 | S30: =R13 -> 3698 | X30: SALDO INPS 2023 | Z30: =Y13 -> 621 | AE30: SALDO INPS 2024 | AG30: =AF13 -> 1364 | AL30: SALDO INPS 2025 | AN30: =AM13 -> 0
C31: ACCONTO INPS 2021 | E31: =D14+D15 -> 1196 | J31: ACCONTO INPS 2022 | L31: =K14+K15 -> 6176.8 | Q31: ACCONTO INPS 2023 | S31: =R14+R15 -> 7900 | X31: ACCONTO INPS 2024 | Z31: =Y14+Y15 -> 6775.2 | AE31: ACCONTO INPS 2025 | AG31: =AF14+AF15 -> 6511.2 | AL31: ACCONTO INPS 2026 | AN31: =AM14+AM15 -> 0
C33: BOLLI FATTURE 2021 | E33: =D19+D20+D21+D22 -> 42 | J33: BOLLI FATTURE 2022 | L33: =K19+K20+K21+K22 -> 46 | Q33: BOLLI FATTURE 2023 | S33: =R19+R20+R21+R22 -> 24 | X33: BOLLI FATTURE 2024 | Z33: =Y19+Y20+Y21+Y22 -> 24 | AE33: BOLLI FATTURE 2025 | AG33: =AF19+AF20+AF21+AF22 -> 22 | AL33: BOLLI FATTURE 2026 | AN33: =AM19+AM20+AM21+AM22 -> 0
C36: CALCOLO TOTALE ANNO 2020 | J36: CALCOLO TOTALE ANNO 2021 | Q36: CALCOLO TOTALE ANNO 2022 | X36: CALCOLO TOTALE ANNO 2023 | AE36: CALCOLO TOTALE ANNO 2024 | AL36: CALCOLO TOTALE ANNO 2025
C38: ERARIO 2020 | E38: =E27 -> 288 | J38: ERARIO 2021 | L38: =E28+L27 -> 1446.62 | Q38: ERARIO 2022 | S38: =L28+S27 -> 1886.64 | X38: ERARIO 2023 | Z38: =S28+Z27 -> 1047.76 | AE38: ERARIO 2024 | AG38: =Z28+AG27 -> 1191 | AL38: ERARIO 2025 | AN38: =AG28+AN27 -> 1191
C39: INPS 2020 | E39: =E30 -> 1480 | J39: INPS 2021 | L39: =E31+L30 -> 7647 | Q39: INPS 2022 | S39: =L31+S30 -> 9874.8 | X39: INPS 2023 | Z39: =S31+Z30 -> 8521 | AE39: INPS 2024 | AG39: =Z31+AG30 -> 8139.2 | AL39: INPS 2025 | AN39: =AG31+AN30 -> 6511.2
C40: BOLLI FATTURE 2020 | E40: 0 | J40: BOLLI FATTURE 2021 | L40: =E33 -> 42 | Q40: BOLLI FATTURE 2022 | S40: =L33 -> 46 | X40: BOLLI FATTURE 2023 | Z40: =S33 -> 24 | AE40: BOLLI FATTURE 2024 | AG40: =Z33 -> 24 | AL40: BOLLI FATTURE 2025 | AN40: =AG33 -> 22
D42: TOTALE '20 | E42: =E38+E39+E40 -> 1768 | K42: TOTALE '21 | L42: =L38+L39+L40 -> 9135.62 | R42: TOTALE '22 | S42: =S38+S39+S40 -> 11807.44 | Y42: TOTALE '23 | Z42: =Z38+Z39+Z40 -> 9592.76 | AF42: TOTALE '24 | AG42: =AG38+AG39+AG40 -> 9354.2 | AM42: TOTALE '25 | AN42: =AN38+AN39+AN40 -> 7724.2
